<?xml version="1.0" encoding="UTF-8"?>
<!DOCTYPE mapper PUBLIC "-//mybatis.org//DTD Mapper 3.0//EN" "http://mybatis.org/dtd/mybatis-3-mapper.dtd">
<mapper namespace="com.sfxie.services.center.dao.mapper.SfxieSysAuthRoleMenuMapper">
  <resultMap id="BaseResultMap" type="com.sfxie.services.center.pojo.SfxieSysAuthRoleMenu">
    <!--
      WARNING - @mbg.generated
      This element is automatically generated by MyBatis Generator, do not modify.
      This element was generated on Mon May 01 19:06:36 CST 2017.
    -->
    <id column="id_" jdbcType="VARCHAR" property="id" />
    <result column="is_valid" jdbcType="CHAR" property="isValid" />
    <result column="role_menu_id" jdbcType="VARCHAR" property="roleMenuId" />
    <result column="auth_data_id" jdbcType="VARCHAR" property="authDataId" />
    <result column="owner_company_code" jdbcType="VARCHAR" property="ownerCompanyCode" />
    <result column="company_role_id" jdbcType="VARCHAR" property="companyRoleId" />
    <result column="partition_company" jdbcType="VARCHAR" property="partitionCompany" />
  </resultMap>
  <sql id="Base_Column_List">
    <!--
      WARNING - @mbg.generated
      This element is automatically generated by MyBatis Generator, do not modify.
      This element was generated on Mon May 01 19:06:36 CST 2017.
    -->
    id_, is_valid, role_menu_id, auth_data_id, owner_company_code, company_role_id, partition_company
  </sql>
  <select id="selectByPrimaryKey" parameterType="com.sfxie.services.center.pojo.SfxieSysAuthRoleMenu" resultMap="BaseResultMap">
    <!--
      WARNING - @mbg.generated
      This element is automatically generated by MyBatis Generator, do not modify.
      This element was generated on Mon May 01 19:06:36 CST 2017.
    -->
    select 
    <include refid="Base_Column_List" />
    from sfxie_sys_auth_role_menu
    where id_ = #{id,jdbcType=VARCHAR}
      and partition_company = #{partitionCompany,jdbcType=VARCHAR}
  </select>
  <delete id="deleteByPrimaryKey" parameterType="com.sfxie.services.center.pojo.SfxieSysAuthRoleMenu">
    <!--
      WARNING - @mbg.generated
      This element is automatically generated by MyBatis Generator, do not modify.
      This element was generated on Mon May 01 19:06:36 CST 2017.
    -->
    delete from sfxie_sys_auth_role_menu
    where id_ = #{id,jdbcType=VARCHAR}
      and partition_company = #{partitionCompany,jdbcType=VARCHAR}
  </delete>
  <insert id="insert" parameterType="com.sfxie.services.center.pojo.SfxieSysAuthRoleMenu">
    <!--
      WARNING - @mbg.generated
      This element is automatically generated by MyBatis Generator, do not modify.
      This element was generated on Mon May 01 19:06:36 CST 2017.
    -->
    insert into sfxie_sys_auth_role_menu (id_, is_valid, role_menu_id, 
      auth_data_id, owner_company_code, company_role_id, 
      partition_company)
    values (#{id,jdbcType=VARCHAR}, #{isValid,jdbcType=CHAR}, #{roleMenuId,jdbcType=VARCHAR}, 
      #{authDataId,jdbcType=VARCHAR}, #{ownerCompanyCode,jdbcType=VARCHAR}, #{companyRoleId,jdbcType=VARCHAR}, 
      #{partitionCompany,jdbcType=VARCHAR})
  </insert>
  <insert id="insertSelective" parameterType="com.sfxie.services.center.pojo.SfxieSysAuthRoleMenu">
    <!--
      WARNING - @mbg.generated
      This element is automatically generated by MyBatis Generator, do not modify.
      This element was generated on Mon May 01 19:06:36 CST 2017.
    -->
    insert into sfxie_sys_auth_role_menu
    <trim prefix="(" suffix=")" suffixOverrides=",">
      <if test="id != null">
        id_,
      </if>
      <if test="isValid != null">
        is_valid,
      </if>
      <if test="roleMenuId != null">
        role_menu_id,
      </if>
      <if test="authDataId != null">
        auth_data_id,
      </if>
      <if test="ownerCompanyCode != null">
        owner_company_code,
      </if>
      <if test="companyRoleId != null">
        company_role_id,
      </if>
      <if test="partitionCompany != null">
        partition_company,
      </if>
    </trim>
    <trim prefix="values (" suffix=")" suffixOverrides=",">
      <if test="id != null">
        #{id,jdbcType=VARCHAR},
      </if>
      <if test="isValid != null">
        #{isValid,jdbcType=CHAR},
      </if>
      <if test="roleMenuId != null">
        #{roleMenuId,jdbcType=VARCHAR},
      </if>
      <if test="authDataId != null">
        #{authDataId,jdbcType=VARCHAR},
      </if>
      <if test="ownerCompanyCode != null">
        #{ownerCompanyCode,jdbcType=VARCHAR},
      </if>
      <if test="companyRoleId != null">
        #{companyRoleId,jdbcType=VARCHAR},
      </if>
      <if test="partitionCompany != null">
        #{partitionCompany,jdbcType=VARCHAR},
      </if>
    </trim>
  </insert>
  <update id="updateByPrimaryKeySelective" parameterType="com.sfxie.services.center.pojo.SfxieSysAuthRoleMenu">
    <!--
      WARNING - @mbg.generated
      This element is automatically generated by MyBatis Generator, do not modify.
      This element was generated on Mon May 01 19:06:36 CST 2017.
    -->
    update sfxie_sys_auth_role_menu
    <set>
      <if test="isValid != null">
        is_valid = #{isValid,jdbcType=CHAR},
      </if>
      <if test="roleMenuId != null">
        role_menu_id = #{roleMenuId,jdbcType=VARCHAR},
      </if>
      <if test="authDataId != null">
        auth_data_id = #{authDataId,jdbcType=VARCHAR},
      </if>
      <if test="ownerCompanyCode != null">
        owner_company_code = #{ownerCompanyCode,jdbcType=VARCHAR},
      </if>
      <if test="companyRoleId != null">
        company_role_id = #{companyRoleId,jdbcType=VARCHAR},
      </if>
      <if test="partitionCompany != null">
        partition_company = #{partitionCompany,jdbcType=VARCHAR},
      </if>
    </set>
    where id_ = #{id,jdbcType=VARCHAR}
      and partition_company = #{partitionCompany,jdbcType=VARCHAR}
  </update>
  <update id="updateByPrimaryKey" parameterType="com.sfxie.services.center.pojo.SfxieSysAuthRoleMenu">
    <!--
      WARNING - @mbg.generated
      This element is automatically generated by MyBatis Generator, do not modify.
      This element was generated on Mon May 01 19:06:36 CST 2017.
    -->
    update sfxie_sys_auth_role_menu
    set is_valid = #{isValid,jdbcType=CHAR},
      role_menu_id = #{roleMenuId,jdbcType=VARCHAR},
      auth_data_id = #{authDataId,jdbcType=VARCHAR},
      owner_company_code = #{ownerCompanyCode,jdbcType=VARCHAR},
      company_role_id = #{companyRoleId,jdbcType=VARCHAR},
      partition_company = #{partitionCompany,jdbcType=VARCHAR}
    where id_ = #{id,jdbcType=VARCHAR}
      and partition_company = #{partitionCompany,jdbcType=VARCHAR}
  </update>
  <select id="selectByCondition" parameterType="com.sfxie.services.center.pojo.SfxieSysAuthRoleMenu" resultMap="BaseResultMap">
    <!--
      WARNING - @mbg.generated
      This element is automatically generated by MyBatis Generator, do not modify.
      This element was generated on Mon May 01 19:06:36 CST 2017.
    -->
    select 
    <include refid="Base_Column_List" />
    from sfxie_sys_auth_role_menu
    where partition_company = #{partitionCompany,jdbcType=VARCHAR}
  </select>
</mapper>